lablift_client/__init__.py
lablift_client/auth.py
lablift_client/biofeature.py
lablift_client/client.py
lablift_client/config.py
lablift_client-0.1.2.dist-info/LICENSE
lablift_client-0.1.2.dist-info/WHEEL
lablift_client-0.1.2.dist-info/METADATA
lablift_client-0.1.2.dist-info/RECORD
