Metadata-Version: 2.1
Name: lablift-client
Version: 0.1.2
Summary: Access LabLift services using Python
Author: Rafael Bizao
Author-email: rabizao@gmail.com
Requires-Python: >=3.8,<4.0
Classifier: Programming Language :: Python :: 3
Classifier: Programming Language :: Python :: 3.10
Classifier: Programming Language :: Python :: 3.8
Classifier: Programming Language :: Python :: 3.9
Requires-Dist: requests (>=2.27.1,<3.0.0)
